j2g/__init__.py
j2g/__main__.py
j2g/json_graph.py
j2g/misc.py
j2g/out.py
jg/__init__.py
jg/__main__.py
jg/json_graph.py
jg/misc.py
jg/out.py
j2g-0.0.1.dist-info/LICENSE.txt
j2g-0.0.1.dist-info/METADATA
j2g-0.0.1.dist-info/WHEEL
j2g-0.0.1.dist-info/top_level.txt
j2g-0.0.1.dist-info/RECORD
