Metadata-Version: 2.1
Name: j2g
Version: 0.0.1
Summary: A json graph util package
Home-page: https://github.com/jeackchn/jg
Author: jeack_chen@hotmail.com
Author-email: jeack_chen@hotmail.com
License: MIT
Project-URL: Bug Tracker, https://github.com/jeackchn/jg/issues
Platform: UNKNOWN
Classifier: Programming Language :: Python :: 3
Classifier: License :: OSI Approved :: MIT License
Classifier: Operating System :: OS Independent
Requires-Python: >=3.6
Requires-Dist: graphviz
